fnb_tex_table_pic/__init__.py
fnb_tex_table_pic/tex_generator.py
fnb_tex_table_pic-0.0.1.dist-info/LICENSE
fnb_tex_table_pic-0.0.1.dist-info/METADATA
fnb_tex_table_pic-0.0.1.dist-info/WHEEL
fnb_tex_table_pic-0.0.1.dist-info/top_level.txt
fnb_tex_table_pic-0.0.1.dist-info/RECORD
